tl/__init__.py
tl/cli_entry.py
tl/exceptions.py
tl/file_formats_validator.py
tl/candidate_generation/__init__.py
tl/candidate_generation/deduplicate_candidates.py
tl/candidate_generation/es_search.py
tl/candidate_generation/get_exact_matches.py
tl/candidate_generation/get_external_identifier_matches.py
tl/candidate_generation/get_fuzzy_augmented_matches.py
tl/candidate_generation/get_fuzzy_matches.py
tl/candidate_generation/get_kgtk_search_matches.py
tl/candidate_generation/get_trigram_matches.py
tl/candidate_generation/ngram_matches.py
tl/candidate_generation/ngram_query.py
tl/candidate_generation/phrase_query_candidates.py
tl/candidate_generation/phrase_query_json.py
tl/candidate_generation/utility.py
tl/candidate_ranking/__init__.py
tl/candidate_ranking/combine_linearly.py
tl/candidate_ranking/predict_using_model.py
tl/cli/__init__.py
tl/cli/add-color.py
tl/cli/add-text-embedding-feature.py
tl/cli/align-page-rank.py
tl/cli/build-elasticsearch-input.py
tl/cli/canonicalize.py
tl/cli/check-candidates.py
tl/cli/check-extra-information.py
tl/cli/clean.py
tl/cli/combine-linearly.py
tl/cli/compute-tf-idf.py
tl/cli/context-match.py
tl/cli/convert-iswc-gt.py
tl/cli/create-groundtruth.py
tl/cli/create-pseudo-gt.py
tl/cli/create-singleton-feature.py
tl/cli/deduplicate-candidates.py
tl/cli/drop-by-score.py
tl/cli/drop-duplicate.py
tl/cli/extract-ground-truth.py
tl/cli/feature-voting.py
tl/cli/generate-reciprocal-rank.py
tl/cli/get-ex-id-matches.py
tl/cli/get-exact-matches.py
tl/cli/get-fuzzy-augmented-matches.py
tl/cli/get-fuzzy-matches.py
tl/cli/get-kg-links.py
tl/cli/get-ngram-matches.py
tl/cli/get-phrase-matches.py
tl/cli/get-trigram-matches.py
tl/cli/ground-truth-labeler.py
tl/cli/join.py
tl/cli/kth-percentile.py
tl/cli/load-elasticsearch-index.py
tl/cli/metrics.py
tl/cli/mosaic-features.py
tl/cli/normalize-scores.py
tl/cli/pgt-semantic-tf-idf.py
tl/cli/pick-hc-candidates.py
tl/cli/plot-score-figure.py
tl/cli/predict-using-model.py
tl/cli/run-pipeline.py
table_linker-0.9.dist-info/LICENSE
table_linker-0.9.dist-info/METADATA
table_linker-0.9.dist-info/WHEEL
table_linker-0.9.dist-info/entry_points.txt
table_linker-0.9.dist-info/top_level.txt
table_linker-0.9.dist-info/RECORD
